idds/__init__.py
idds/atlas/__init__.py
idds/atlas/version.py
idds/atlas/notifier/__init__.py
idds/atlas/notifier/messaging.py
idds/atlas/processing/__init__.py
idds/atlas/processing/activelearning_condor_poller.py
idds/atlas/processing/activelearning_condor_submitter.py
idds/atlas/processing/base_plugin.py
idds/atlas/processing/condor_poller.py
idds/atlas/processing/condor_submitter.py
idds/atlas/processing/hyperparameteropt_bayesian.py
idds/atlas/processing/hyperparameteropt_condor_poller.py
idds/atlas/processing/hyperparameteropt_condor_submitter.py
idds/atlas/processing/hyperparameteropt_nevergrad.py
idds/atlas/processing/stagein_poller.py
idds/atlas/processing/stagein_submitter.py
idds/atlas/rucio/__init__.py
idds/atlas/rucio/base_plugin.py
idds/atlas/rucio/collection_lister.py
idds/atlas/rucio/collection_metadata_reader.py
idds/atlas/rucio/contents_lister.py
idds/atlas/rucio/contents_register.py
idds/atlas/rucio/rule_creator.py
idds/atlas/rucio/rule_poller.py
idds/atlas/rucio/rule_submitter.py
idds/atlas/transformer/__init__.py
idds/atlas/transformer/activelearning_transformer.py
idds/atlas/transformer/base_plugin.py
idds/atlas/transformer/hyperparameteropt_transformer.py
idds/atlas/transformer/stagein_transformer.py
idds/atlas/workflow/__init__.py
idds/atlas/workflow/atlasactuatorwork.py
idds/atlas/workflow/atlascondorwork.py
idds/atlas/workflow/atlasdagwork.py
idds/atlas/workflow/atlashpowork.py
idds/atlas/workflow/atlaslocalpandawork.py
idds/atlas/workflow/atlaspandawork.py
idds/atlas/workflow/atlasstageinwork.py
idds/atlas/workflowv2/__init__.py
idds/atlas/workflowv2/atlasactuatorwork.py
idds/atlas/workflowv2/atlascondorwork.py
idds/atlas/workflowv2/atlasdagwork.py
idds/atlas/workflowv2/atlashpowork.py
idds/atlas/workflowv2/atlaslocalpandawork.py
idds/atlas/workflowv2/atlaspandawork.py
idds/atlas/workflowv2/atlasstageinwork.py
idds_atlas-2.0.9.data/data/tools/env/environment.yml
idds_atlas-2.0.9.dist-info/LICENSE.rst
idds_atlas-2.0.9.dist-info/METADATA
idds_atlas-2.0.9.dist-info/WHEEL
idds_atlas-2.0.9.dist-info/top_level.txt
idds_atlas-2.0.9.dist-info/RECORD
