Metadata-Version: 2.1
Name: idds-atlas
Version: 2.0.9
Summary: intelligent Data Delivery Service(iDDS) Package
Author: IRIS-HEP Team
Author-email: atlas-adc-panda@cern.ch
License: GPL
Project-URL: Documentation, https://github.com/HSF/iDDS/wiki
Project-URL: Source, https://github.com/HSF/iDDS
Classifier: Development Status :: 5 - Production/Stable
Classifier: Intended Audience :: Developers
Classifier: Natural Language :: English
Classifier: Programming Language :: Python :: 3.6
Requires-Python: >=3.6
License-File: LICENSE.rst
Requires-Dist: pip
Requires-Dist: futures
Requires-Dist: unittest2
Requires-Dist: pep8
Requires-Dist: flake8
Requires-Dist: pytest
Requires-Dist: nose
Requires-Dist: stomp.py
Requires-Dist: panda-client-light
Requires-Dist: rucio-clients
Requires-Dist: rucio-clients-atlas
Requires-Dist: idds-common ==2.0.9
Requires-Dist: idds-workflow ==2.0.9
